chonker/__init__.py
chonker/chonker.py
chonkify-1.0.0.dist-info/LICENSE
chonkify-1.0.0.dist-info/METADATA
chonkify-1.0.0.dist-info/WHEEL
chonkify-1.0.0.dist-info/top_level.txt
chonkify-1.0.0.dist-info/RECORD
